LICENSE
MANIFEST.in
readme.md
setup.cfg
setup.py
solrdataimport/__init__.py
solrdataimport/dataimport.py
solrdataimport/payload.py
solrdataimport.egg-info/PKG-INFO
solrdataimport.egg-info/SOURCES.txt
solrdataimport.egg-info/dependency_links.txt
solrdataimport.egg-info/not-zip-safe
solrdataimport.egg-info/requires.txt
solrdataimport.egg-info/top_level.txt
solrdataimport/cass/__init__.py
solrdataimport/cass/cassClient.py
solrdataimport/cass/cassSchema.py
solrdataimport/dataload/__init__.py
solrdataimport/dataload/cassdata.py
solrdataimport/dataload/fetch.py
solrdataimport/lib/__init__.py
solrdataimport/lib/cache.py
solrdataimport/lib/map.py
solrdataimport/lib/util.py
solrdataimport/solr/__init__.py
solrdataimport/solr/solrclient.py
solrdataimport/solr/solrexport.py
solrdataimport/solr/solrschema.py