Metadata-Version: 1.1
Name: solrdataimport
Version: 1.0.2
Summary: Data import from cassandra to solr
Home-page: https://github.com/pisceanfoot/solrdataimport
Author: Leo He
Author-email: pisceanfoot@gmail.com
License: Apache 2.0
Platform: UNKNOWN
Classifier: Development Status :: 5 - Production/Stable
Classifier: Intended Audience :: Developers
Classifier: Natural Language :: English
Classifier: License :: OSI Approved :: Apache Software License
Classifier: Programming Language :: Python
Classifier: Programming Language :: Python :: 2.7
Classifier: Programming Language :: Python :: Implementation :: CPython
Classifier: Programming Language :: Python :: Implementation :: PyPy
